{
  "books": [
    {
      "id": "book_1_001",
      "title": "Pai Rico, Pai Pobre",
      "author": "Robert Kiyosaki",
      "description": "O livro mais vendido sobre educação financeira, que mudou a forma como milhões de pessoas pensam sobre dinheiro e investimentos.",
      "category": "Educação Financeira",
      "coverImageURL": "https://images.unsplash.com/photo-1589829545856-d10d557cf95f?w=400",
      "digitalPrice": 15000,
      "physicalPrice": 25000,
      "digitalFormat": "PDF, EPUB",
      "hasPhysicalVersion": true,
      "weight": "350g",
      "pages": 336,
      "publisher": "Alta Books",
      "publicationYear": "2017",
      "isbn": "978-8550801469",
      "language": "Português",
      "downloadInfo": "Após a compra, o livro estará disponível para download imediato",
      "sellerName": "Livraria Premium",
      "rating": 4.8,
      "totalReviews": 2543
    },
    {
      "id": "book_1_002",
      "title": "O Investidor Inteligente",
      "author": "Benjamin Graham",
      "description": "A bíblia do mercado de valores. Um guia clássico sobre investimentos em valor.",
      "category": "Investimentos",
      "coverImageURL": "https://images.unsplash.com/photo-1544947950-fa07a98d237f?w=400",
      "digitalPrice": 18000,
      "physicalPrice": 30000,
      "digitalFormat": "PDF, EPUB, MOBI",
      "hasPhysicalVersion": true,
      "weight": "520g",
      "pages": 672,
      "publisher": "HarperCollins",
      "publicationYear": "2016",
      "isbn": "978-8595080805",
      "language": "Português",
      "downloadInfo": "Download em múltiplos formatos",
      "sellerName": "Bookstore Angola",
      "rating": 4.9,
      "totalReviews": 1876
    },
    {
      "id": "book_1_003",
      "title": "Segredos da Mente Milionária",
      "author": "T. Harv Eker",
      "description": "Aprenda os padrões de pensamento que separam os ricos dos pobres.",
      "category": "Finanças Pessoais",
      "coverImageURL": "https://images.unsplash.com/photo-1553729459-efe14ef6055d?w=400",
      "digitalPrice": 12000,
      "physicalPrice": 22000,
      "digitalFormat": "PDF, EPUB",
      "hasPhysicalVersion": true,
      "weight": "280g",
      "pages": 176,
      "publisher": "Sextante",
      "publicationYear": "2018",
      "isbn": "978-8543105048",
      "language": "Português",
      "downloadInfo": "Acesso imediato após confirmação",
      "sellerName": "Livraria Premium",
      "rating": 4.7,
      "totalReviews": 3201
    }
  ],
  "metadata": {
    "version": "1.0.0",
    "fileNumber": 1,
    "totalBooks": 3,
    "lastUpdated": "2025-11-09T00:00:00Z"
  }
}